README.md
setup.py
django_co_obj_su.egg-info/PKG-INFO
django_co_obj_su.egg-info/SOURCES.txt
django_co_obj_su.egg-info/dependency_links.txt
django_co_obj_su.egg-info/requires.txt
django_co_obj_su.egg-info/top_level.txt
django_conoha_objstorage/__init__.py
django_conoha_objstorage/admin.py
django_conoha_objstorage/api.py
django_conoha_objstorage/apps.py
django_conoha_objstorage/backend.py
django_conoha_objstorage/models.py
django_conoha_objstorage/tests.py
django_conoha_objstorage/views.py