Metadata-Version: 2.1
Name: django-co-obj-su
Version: 0.0.2
Summary: django conoha object storage for summernote
Home-page: UNKNOWN
Author: yukoishii
Author-email: yuko.ishii.1012@gmail.com
License: MIT
Platform: UNKNOWN
Classifier: License :: OSI Approved :: MIT License
Classifier: Programming Language :: Python :: 3.7
